devart/dynamicsbc/__init__.py
devart/dynamicsbc/dynamicsbc.cp38-win_amd64.pyd
devart/dynamicsbc/dynamicsbc.pyi
devart/dynamicsbc/DynamicsBC/Devart.Python.DynamicsBCEngine.dll
devart/dynamicsbc/DynamicsBC/sqlite3.dll
devart/dynamicsbc/sqlalchemy/__init__.py
devart_dynamicsbc_connector-1.0.1.dist-info/LICENSE
devart_dynamicsbc_connector-1.0.1.dist-info/METADATA
devart_dynamicsbc_connector-1.0.1.dist-info/WHEEL
devart_dynamicsbc_connector-1.0.1.dist-info/top_level.txt
devart_dynamicsbc_connector-1.0.1.dist-info/RECORD
